dash_holoniq_apexcharts/DashApexcharts.py
dash_holoniq_apexcharts/__init__.py
dash_holoniq_apexcharts/_imports_.py
dash_holoniq_apexcharts/dash_holoniq_apexcharts.dev.js
dash_holoniq_apexcharts/dash_holoniq_apexcharts.dev.js.map
dash_holoniq_apexcharts/dash_holoniq_apexcharts.min.js
dash_holoniq_apexcharts/dash_holoniq_apexcharts.min.js.map
dash_holoniq_apexcharts/metadata.json
dash_holoniq_apexcharts/package-info.json
dash_holoniq_apexcharts-0.0.6.dist-info/LICENSE
dash_holoniq_apexcharts-0.0.6.dist-info/METADATA
dash_holoniq_apexcharts-0.0.6.dist-info/WHEEL
dash_holoniq_apexcharts-0.0.6.dist-info/top_level.txt
dash_holoniq_apexcharts-0.0.6.dist-info/RECORD
