Metadata-Version: 2.1
Name: dash_holoniq_apexcharts
Version: 0.0.6
Summary: Dash wrapper for apexcharts library
Home-page: UNKNOWN
Author: Stave Jones <jonesst2608@gmail.com>
License: MIT
Platform: UNKNOWN
Classifier: Framework :: Dash
License-File: LICENSE
